ctshed/__init__.py
ctshed/cli.py
ctshed/constants.py
ctshed/container.py
ctshed/ctshed.py
ctshed/executable.py
ctshed/options.py
ctshed/utils.py
ctshed-0.1.1.dist-info/LICENSE
ctshed-0.1.1.dist-info/METADATA
ctshed-0.1.1.dist-info/WHEEL
ctshed-0.1.1.dist-info/entry_points.txt
ctshed-0.1.1.dist-info/top_level.txt
ctshed-0.1.1.dist-info/RECORD
