Metadata-Version: 2.1
Name: ctshed
Version: 0.1.1
Summary: A Docker based CLI Tools manager.
Home-page: https://github.com/kkarolis/ctshed
License: UNKNOWN
Platform: UNKNOWN
Classifier: Development Status :: 3 - Alpha
Classifier: Intended Audience :: Developers
Classifier: License :: OSI Approved :: MIT License
Classifier: Programming Language :: Python :: 3.7
Requires-Dist: Click
Requires-Dist: jinja2
